{
    "id": "2ec81d2c6c8c43708e96bf3055bd6e36",
    "title": "Past Perfect Continuous Positive",
    "questions": [
        {
            "parts": [
                {
                    "type": "text",
                    "value": "I"
                },
                {
                    "type": "input",
                    "answers": [
                        "had been working",
                        "'d been working"
                    ]
                },
                {
                    "type": "text",
                    "value": "(work) all day, so I didn't want to go out.."
                }
            ]
        },
        {
            "parts": [
                {
                    "type": "text",
                    "value": "She"
                },
                {
                    "type": "input",
                    "answers": [
                        "had been sleeping",
                        "'d been sleeping"
                    ]
                },
                {
                    "type": "text",
                    "value": "(sleep) for ten hours when I woke her."
                }
            ]
        },
        {
            "parts": [
                {
                    "type": "text",
                    "value": "They"
                },
                {
                    "type": "input",
                    "answers": [
                        "had been living",
                        "'d been living"
                    ]
                },
                {
                    "type": "text",
                    "value": "(live) in Beijing for three years when he lost his job."
                }
            ]
        },
        {
            "parts": [
                {
                    "type": "text",
                    "value": "When we met, you"
                },
                {
                    "type": "input",
                    "answers": [
                        "had been working",
                        "'d been working"
                    ]
                },
                {
                    "type": "text",
                    "value": "(work) at that company for six months."
                }
            ]
        },
        {
            "parts": [
                {
                    "type": "text",
                    "value": "We"
                },
                {
                    "type": "input",
                    "answers": [
                        "had been eating",
                        "'d been eating"
                    ]
                },
                {
                    "type": "text",
                    "value": "(eat) all day, so we felt a bit ill."
                }
            ]
        },
        {
            "parts": [
                {
                    "type": "text",
                    "value": "He was red in the face because he"
                },
                {
                    "type": "input",
                    "answers": [
                        "had been running",
                        "'d been running"
                    ]
                },
                {
                    "type": "text",
                    "value": "(run) ."
                }
            ]
        },
        {
            "parts": [
                {
                    "type": "text",
                    "value": "It"
                },
                {
                    "type": "input",
                    "answers": [
                        "had been raining",
                        "'d been raining"
                    ]
                },
                {
                    "type": "text",
                    "value": "(rain) and the road was covered in water."
                }
            ]
        },
        {
            "parts": [
                {
                    "type": "text",
                    "value": "I was really tired because I"
                },
                {
                    "type": "input",
                    "answers": [
                        "had been studying",
                        "'d been studying"
                    ]
                },
                {
                    "type": "text",
                    "value": "(study) ."
                }
            ]
        },
        {
            "parts": [
                {
                    "type": "text",
                    "value": "We"
                },
                {
                    "type": "input",
                    "answers": [
                        "had been going",
                        "'d been going out"
                    ]
                },
                {
                    "type": "text",
                    "value": "(go) out for three years when we got married."
                }
            ]
        },
        {
            "parts": [
                {
                    "type": "text",
                    "value": "It"
                },
                {
                    "type": "input",
                    "answers": [
                        "had been snowing",
                        "'d been snowing"
                    ]
                },
                {
                    "type": "text",
                    "value": "(snow) for three days."
                }
            ]
        }
    ]
}