{
    "id": "90141b82b18f4f42a882960f130b0b49",
    "title": "Past Simple All Forms Mixed Exercise 3",
    "questions": [
        {
            "parts": [
                {
                    "type": "text",
                    "value": "She"
                },
                {
                    "type": "input",
                    "answers": [
                        "went"
                    ]
                },
                {
                    "type": "text",
                    "value": "(go) home."
                }
            ]
        },
        {
            "parts": [
                {
                    "type": "text",
                    "value": "We"
                },
                {
                    "type": "input",
                    "answers": [
                        "watched"
                    ]
                },
                {
                    "type": "text",
                    "value": "(watch) a film."
                }
            ]
        },
        {
            "parts": [
                {
                    "type": "text",
                    "value": "When"
                },
                {
                    "type": "input",
                    "answers": [
                        "did he arrive"
                    ]
                },
                {
                    "type": "text",
                    "value": "(he/arrive)?"
                }
            ]
        },
        {
            "parts": [
                {
                    "type": "text",
                    "value": "I"
                },
                {
                    "type": "input",
                    "answers": [
                        "bought"
                    ]
                },
                {
                    "type": "text",
                    "value": "(buy) a new car."
                }
            ]
        },
        {
            "parts": [
                {
                    "type": "text",
                    "value": "Where"
                },
                {
                    "type": "input",
                    "answers": [
                        "did you live"
                    ]
                },
                {
                    "type": "text",
                    "value": "(you/live)?"
                }
            ]
        },
        {
            "parts": [
                {
                    "type": "text",
                    "value": "I"
                },
                {
                    "type": "input",
                    "answers": [
                        "played"
                    ]
                },
                {
                    "type": "text",
                    "value": "(play) tennis."
                }
            ]
        },
        {
            "parts": [
                {
                    "type": "text",
                    "value": "Where"
                },
                {
                    "type": "input",
                    "answers": [
                        "did you work"
                    ]
                },
                {
                    "type": "text",
                    "value": "(you/work) before?"
                }
            ]
        },
        {
            "parts": [
                {
                    "type": "input",
                    "answers": [
                        "Did they come"
                    ]
                },
                {
                    "type": "text",
                    "value": "(they/come) for lunch?"
                }
            ]
        },
        {
            "parts": [
                {
                    "type": "input",
                    "answers": [
                        "Did we study"
                    ]
                },
                {
                    "type": "text",
                    "value": "(we/study) this last year?"
                }
            ]
        },
        {
            "parts": [
                {
                    "type": "text",
                    "value": "They"
                },
                {
                    "type": "input",
                    "answers": [
                        "drank"
                    ]
                },
                {
                    "type": "text",
                    "value": "(drink) coffee."
                }
            ]
        },
        {
            "parts": [
                {
                    "type": "input",
                    "answers": [
                        "Did you see"
                    ]
                },
                {
                    "type": "text",
                    "value": "(you/see) that film?"
                }
            ]
        },
        {
            "parts": [
                {
                    "type": "text",
                    "value": "We"
                },
                {
                    "type": "input",
                    "answers": [
                        "ate"
                    ]
                },
                {
                    "type": "text",
                    "value": "(eat) dinner."
                }
            ]
        },
        {
            "parts": [
                {
                    "type": "text",
                    "value": "You"
                },
                {
                    "type": "input",
                    "answers": [
                        "didn't go",
                        "did not go"
                    ]
                },
                {
                    "type": "text",
                    "value": "(not/go) out last night."
                }
            ]
        },
        {
            "parts": [
                {
                    "type": "text",
                    "value": "He"
                },
                {
                    "type": "input",
                    "answers": [
                        "studied"
                    ]
                },
                {
                    "type": "text",
                    "value": "(study)."
                }
            ]
        },
        {
            "parts": [
                {
                    "type": "text",
                    "value": "What"
                },
                {
                    "type": "input",
                    "answers": [
                        "did you watch"
                    ]
                },
                {
                    "type": "text",
                    "value": "(you/watch)?"
                }
            ]
        },
        {
            "parts": [
                {
                    "type": "text",
                    "value": "we"
                },
                {
                    "type": "input",
                    "answers": [
                        "didn't call",
                        "did not call"
                    ]
                },
                {
                    "type": "text",
                    "value": "(not/call) you yesterday."
                }
            ]
        },
        {
            "parts": [
                {
                    "type": "text",
                    "value": "They"
                },
                {
                    "type": "input",
                    "answers": [
                        "didn't arrive",
                        "did not arrive"
                    ]
                },
                {
                    "type": "text",
                    "value": "(not/arrive) on time."
                }
            ]
        },
        {
            "parts": [
                {
                    "type": "text",
                    "value": "It"
                },
                {
                    "type": "input",
                    "answers": [
                        "didn't rain",
                        "did not rain"
                    ]
                },
                {
                    "type": "text",
                    "value": "(not/rain)."
                }
            ]
        },
        {
            "parts": [
                {
                    "type": "text",
                    "value": "We"
                },
                {
                    "type": "input",
                    "answers": [
                        "didn't drink",
                        "did not drink"
                    ]
                },
                {
                    "type": "text",
                    "value": "(not/drink) beer."
                }
            ]
        },
        {
            "parts": [
                {
                    "type": "text",
                    "value": "You"
                },
                {
                    "type": "input",
                    "answers": [
                        "cleaned"
                    ]
                },
                {
                    "type": "text",
                    "value": "(clean) the kitchen."
                }
            ]
        }
    ]
}