{
    "id": "95803c84117941a0abec2896747a50ed",
    "title": "Present Simple 'Wh' Questions with 'be'",
    "questions": [
        {
            "parts": [
                {
                    "type": "text",
                    "value": "Where / John?"
                },
                {
                    "type": "input",
                    "answers": [
                        "Where is John?"
                    ]
                }
            ]
        },
        {
            "parts": [
                {
                    "type": "text",
                    "value": "Why / they / hungry?"
                },
                {
                    "type": "input",
                    "answers": [
                        "Why are they hungry?"
                    ]
                }
            ]
        },
        {
            "parts": [
                {
                    "type": "text",
                    "value": "Where / we?"
                },
                {
                    "type": "input",
                    "answers": [
                        "Where are we?"
                    ]
                }
            ]
        },
        {
            "parts": [
                {
                    "type": "text",
                    "value": "Who / you?"
                },
                {
                    "type": "input",
                    "answers": [
                        "Who are you?"
                    ]
                }
            ]
        },
        {
            "parts": [
                {
                    "type": "text",
                    "value": "Why / he / late?"
                },
                {
                    "type": "input",
                    "answers": [
                        "Why is he late?"
                    ]
                }
            ]
        },
        {
            "parts": [
                {
                    "type": "text",
                    "value": "What / this?"
                },
                {
                    "type": "input",
                    "answers": [
                        "What is this?"
                    ]
                }
            ]
        },
        {
            "parts": [
                {
                    "type": "text",
                    "value": "Where / Jimmy?"
                },
                {
                    "type": "input",
                    "answers": [
                        "Where is Jimmy?"
                    ]
                }
            ]
        },
        {
            "parts": [
                {
                    "type": "text",
                    "value": "How old / she?"
                },
                {
                    "type": "input",
                    "answers": [
                        "How old is she?"
                    ]
                }
            ]
        },
        {
            "parts": [
                {
                    "type": "text",
                    "value": "How / you?"
                },
                {
                    "type": "input",
                    "answers": [
                        "How are you?"
                    ]
                }
            ]
        },
        {
            "parts": [
                {
                    "type": "text",
                    "value": "Where / the station?"
                },
                {
                    "type": "input",
                    "answers": [
                        "Where is the station?"
                    ]
                }
            ]
        },
        {
            "parts": [
                {
                    "type": "text",
                    "value": "What time / it now?"
                },
                {
                    "type": "input",
                    "answers": [
                        "What time is it now?"
                    ]
                }
            ]
        },
        {
            "parts": [
                {
                    "type": "text",
                    "value": "Where / Pedro / from?"
                },
                {
                    "type": "input",
                    "answers": [
                        "Where is Pedro from?"
                    ]
                }
            ]
        },
        {
            "parts": [
                {
                    "type": "text",
                    "value": "Why / they / in the kitchen?"
                },
                {
                    "type": "input",
                    "answers": [
                        "Why are they in the kitchen?"
                    ]
                }
            ]
        },
        {
            "parts": [
                {
                    "type": "text",
                    "value": "How / the food?"
                },
                {
                    "type": "input",
                    "answers": [
                        "How is the food?"
                    ]
                }
            ]
        },
        {
            "parts": [
                {
                    "type": "text",
                    "value": "How long / the journey?"
                },
                {
                    "type": "input",
                    "answers": [
                        "How long is the journey?"
                    ]
                }
            ]
        },
        {
            "parts": [
                {
                    "type": "text",
                    "value": "How old / you?"
                },
                {
                    "type": "input",
                    "answers": [
                        "How old are you?"
                    ]
                }
            ]
        },
        {
            "parts": [
                {
                    "type": "text",
                    "value": "Why / I / last?"
                },
                {
                    "type": "input",
                    "answers": [
                        "Why am I last?"
                    ]
                }
            ]
        },
        {
            "parts": [
                {
                    "type": "text",
                    "value": "What time / the concert?"
                },
                {
                    "type": "input",
                    "answers": [
                        "What time is the concert?"
                    ]
                }
            ]
        },
        {
            "parts": [
                {
                    "type": "text",
                    "value": "Where / she?"
                },
                {
                    "type": "input",
                    "answers": [
                        "Where is she?"
                    ]
                }
            ]
        },
        {
            "parts": [
                {
                    "type": "text",
                    "value": "Who / Julie / with?"
                },
                {
                    "type": "input",
                    "answers": [
                        "Who is Julie with?"
                    ]
                }
            ]
        }
    ]
}