{
    "id": "619346ac42ed4703affb9671b9493a91",
    "title": "Sentence Completion Exercise",
    "questions": [
        {
            "question": "It is ......................... hot to go out.",
            "description": "",
            "answers": [
                "too",
                "so",
                "enough"
            ],
            "correct": 0
        },
        {
            "question": "You must hurry, ............................. you will miss the train.",
            "description": "",
            "answers": [
                "unless",
                "if",
                "or else"
            ],
            "correct": 2
        },
        {
            "question": "............................... a noise, the thief ran away.",
            "description": "",
            "answers": [
                "Hearing",
                "Heard",
                "Hear"
            ],
            "correct": 0
        },
        {
            "question": "The weather ......................... fine, we decided to go for a walk.",
            "description": "",
            "answers": [
                "is",
                "was",
                "being"
            ],
            "correct": 2
        },
        {
            "question": "If he .............................. hard, he would not have failed.",
            "description": "",
            "answers": [
                "worked",
                "has worked",
                "had worked"
            ],
            "correct": 2
        },
        {
            "question": "................................ his hard work, he failed to pass the test.",
            "description": "",
            "answers": [
                "Despite",
                "Though",
                "However"
            ],
            "correct": 0
        },
        {
            "question": "Whenever he saw a dog, he threw stones ............................ it.",
            "description": "",
            "answers": [
                "on",
                "at",
                "to"
            ],
            "correct": 1
        },
        {
            "question": "She speaks ................................. she knows everything.",
            "description": "",
            "answers": [
                "like",
                "as if",
                "though"
            ],
            "correct": 1
        },
        {
            "question": ".......................... I didn’t know anybody at the party, I had a good time.",
            "description": "",
            "answers": [
                "Even if",
                "Even though",
                "As if"
            ],
            "correct": 1
        },
        {
            "question": "I want to know .................................. he is absent.",
            "description": "",
            "answers": [
                "that",
                "why",
                "what"
            ],
            "correct": 1
        },
        {
            "question": "She does not know what ............................ doing.",
            "description": "",
            "answers": [
                "is she",
                "she is",
                "Either could be used here"
            ],
            "correct": 1
        },
        {
            "question": "I prefer reading books ............................... television.",
            "description": "",
            "answers": [
                "to watch",
                "to watching",
                "over watching"
            ],
            "correct": 1
        },
        {
            "question": ".............................. his illness, he attends office regularly.",
            "description": "",
            "answers": [
                "In spite of",
                "Despite",
                "Either could be used here"
            ],
            "correct": 2
        },
        {
            "question": "She was ............................ tired that she could not walk.",
            "description": "",
            "answers": [
                "too",
                "so",
                "enough"
            ],
            "correct": 1
        },
        {
            "question": "This is the house ............................. Jack built.",
            "description": "",
            "answers": [
                "who",
                "what",
                "that"
            ],
            "correct": 2
        }
    ]
}