{
    "id": "6bd689b6d6d1485eac605edbd052c084",
    "title": "Passive Voice Exercise",
    "questions": [
        {
            "question": "The parcels …………………",
            "description": "",
            "answers": [
                "have sent",
                "have being sent",
                "have been sent"
            ],
            "correct": 2
        },
        {
            "question": "The performance ………………… by the spectators.",
            "description": "",
            "answers": [
                "applauded",
                "has applauded",
                "was applauded"
            ],
            "correct": 2
        },
        {
            "question": "The culprits ………………….. by the police.",
            "description": "",
            "answers": [
                "arrested",
                "have arrested",
                "have been arrested"
            ],
            "correct": 2
        },
        {
            "question": "The work …………………. in a week.",
            "description": "",
            "answers": [
                "will finish",
                "will be finishing",
                "will be finished"
            ],
            "correct": 2
        },
        {
            "question": "The boy ………………….. by the teacher.",
            "description": "",
            "answers": [
                "praised",
                "has praised",
                "was praised"
            ],
            "correct": 2
        },
        {
            "question": "We ……………….. grammar by Mr. James.",
            "description": "",
            "answers": [
                "are teaching",
                "have taught",
                "are taught"
            ],
            "correct": 2
        },
        {
            "question": "My pen ………………… .",
            "description": "",
            "answers": [
                "has stolen",
                "stole",
                "has been stolen"
            ],
            "correct": 2
        },
        {
            "question": "The horse …………………. by the sudden noise.",
            "description": "",
            "answers": [
                "frightened",
                "has frightened",
                "was frightened"
            ],
            "correct": 2
        },
        {
            "question": "The boy ………………….. by their servant.",
            "description": "",
            "answers": [
                "abducted",
                "has abducted",
                "was abducted"
            ],
            "correct": 2
        },
        {
            "question": "This portrait …………………. by my grandmother.",
            "description": "",
            "answers": [
                "painted",
                "has painted",
                "was painted"
            ],
            "correct": 2
        }
    ]
}