{
    "id": "7f8ab4ad739a46f883dc35b93406bbae",
    "title": "Vocabulary Exercise",
    "questions": [
        {
            "question": "After finishing his work, he ………………………. down to rest.",
            "description": "Lay is the past tense of to lie.",
            "answers": [
                "lie",
                "lay",
                "lain"
            ],
            "correct": 1
        },
        {
            "question": "As they have no children, they ………………………… an orphan.",
            "description": "To adopt a child is to take as one's own.",
            "answers": [
                "adapted",
                "adopted"
            ],
            "correct": 1
        },
        {
            "question": "After the operation, the patient was kept in the intensive care unit for close …………………………….",
            "description": "Observance is a customary practice. ",
            "answers": [
                "observance",
                "observation"
            ],
            "correct": 1
        },
        {
            "question": "Keep ………………………… otherwise the bird might become frightened.",
            "description": "",
            "answers": [
                "quite",
                "quiet"
            ],
            "correct": 1
        },
        {
            "question": "He was an …………………………. person.",
            "description": "Amiable means pleasing or agreeable. ",
            "answers": [
                "amiable",
                "amicable"
            ],
            "correct": 0
        },
        {
            "question": "It is a …………………………… report.",
            "description": "Confidential means intended to be kept private.",
            "answers": [
                "confident",
                "confidential"
            ],
            "correct": 1
        },
        {
            "question": "Now that everyone ………………………….. come, we can start the program.",
            "description": "Use a singular verb after everyone. ",
            "answers": [
                "has",
                "have"
            ],
            "correct": 0
        },
        {
            "question": "Day and night come ………………………….",
            "description": "",
            "answers": [
                "alternately",
                "alternatively"
            ],
            "correct": 0
        },
        {
            "question": "The management refused to ……………………………. the demand of the employees.",
            "description": "Grand means magnificent. ",
            "answers": [
                "grant",
                "grand"
            ],
            "correct": 0
        },
        {
            "question": "The tallest of the three buildings …………………………… to my grandfather.",
            "description": "Here the subject is the singular expression the tallest. ",
            "answers": [
                "belong",
                "belongs"
            ],
            "correct": 1
        },
        {
            "question": "The company set up a committee to look into the ………………………….. of its employees.",
            "description": "A grievance is a complaint. ",
            "answers": [
                "grief",
                "grievance"
            ],
            "correct": 1
        },
        {
            "question": "The old house is ………………………….. with spiders and rats.",
            "description": "If a place is infested with rats, they are present in large numbers. ",
            "answers": [
                "infected",
                "infested"
            ],
            "correct": 1
        }
    ]
}